MANIFEST.in
README.rst
setup.py
walkscore_frontend/__init__.py
walkscore_frontend/frontend.py
walkscore_frontend/http.py
walkscore_frontend/regex.py
walkscore_frontend/utils.py
walkscore_frontend/wslocation.py
walkscore_frontend.egg-info/PKG-INFO
walkscore_frontend.egg-info/SOURCES.txt
walkscore_frontend.egg-info/dependency_links.txt
walkscore_frontend.egg-info/not-zip-safe
walkscore_frontend.egg-info/requires.txt
walkscore_frontend.egg-info/top_level.txt