Metadata-Version: 1.1
Name: walkscore-frontend
Version: 0.3
Summary: Front-end (scraper API) for the Walkscore website
Home-page: http://github.com/evilsoapbox/walkscore_frontend
Author: James Malone
Author-email: jamalone@gmail.com
License: MIT
Keywords: walkscore frontend data walk transitscore bikescore
Platform: UNKNOWN
Classifier: Development Status :: 3 - Alpha
Classifier: License :: OSI Approved :: MIT License
Classifier: Programming Language :: Python :: 2.7
Classifier: Topic :: Scientific/Engineering :: GIS
Classifier: Natural Language :: English
Classifier: Intended Audience :: Science/Research
